ps7_tool/__init__.py
ps7_tool/mcp_server.py
ps7_tool/ps7_executor.py
ps7_mcp_tool-1.0.6.dist-info/METADATA
ps7_mcp_tool-1.0.6.dist-info/WHEEL
ps7_mcp_tool-1.0.6.dist-info/entry_points.txt
ps7_mcp_tool-1.0.6.dist-info/top_level.txt
ps7_mcp_tool-1.0.6.dist-info/RECORD
