Metadata-Version: 2.4
Name: ps7-mcp-tool
Version: 1.0.6
Summary: PowerShell 7 MCP Server for Zencoder - Execute PowerShell commands via MCP protocol
Author-email: Nomad <nomad@example.com>
License: MIT
Project-URL: Homepage, https://github.com/yourusername/ps7-mcp-tool
Project-URL: Documentation, https://github.com/yourusername/ps7-mcp-tool#readme
Keywords: mcp,powershell,zencoder,tool
Classifier: Development Status :: 4 - Beta
Classifier: Intended Audience :: Developers
Classifier: License :: OSI Approved :: MIT License
Classifier: Operating System :: Microsoft :: Windows
Classifier: Operating System :: POSIX :: Linux
Classifier: Operating System :: MacOS
Classifier: Programming Language :: Python :: 3
Classifier: Programming Language :: Python :: 3.8
Classifier: Programming Language :: Python :: 3.9
Classifier: Programming Language :: Python :: 3.10
Classifier: Programming Language :: Python :: 3.11
Classifier: Programming Language :: Python :: 3.12
Classifier: Programming Language :: Python :: 3.13
Requires-Python: >=3.8
